_blackish_version.py
blackish/__init__.py
blackish/__main__.py
blackish/brackets.py
blackish/cache.py
blackish/comments.py
blackish/concurrency.py
blackish/const.py
blackish/debug.py
blackish/files.py
blackish/handle_ipynb_magics.py
blackish/linegen.py
blackish/lines.py
blackish/mode.py
blackish/nodes.py
blackish/numerics.py
blackish/output.py
blackish/parsing.py
blackish/py.typed
blackish/report.py
blackish/rusty.py
blackish/strings.py
blackish/trans.py
blackishd/__init__.py
blackishd/__main__.py
blackishd/middlewares.py
blib2to3/Grammar.txt
blib2to3/PatternGrammar.txt
blib2to3/__init__.py
blib2to3/pygram.py
blib2to3/pytree.py
blib2to3/pgen2/__init__.py
blib2to3/pgen2/conv.py
blib2to3/pgen2/driver.py
blib2to3/pgen2/grammar.py
blib2to3/pgen2/literals.py
blib2to3/pgen2/parse.py
blib2to3/pgen2/pgen.py
blib2to3/pgen2/token.py
blib2to3/pgen2/tokenize.py
blackish-22.6.5.dist-info/AUTHORS.md
blackish-22.6.5.dist-info/LICENSE
blackish-22.6.5.dist-info/METADATA
blackish-22.6.5.dist-info/WHEEL
blackish-22.6.5.dist-info/entry_points.txt
blackish-22.6.5.dist-info/top_level.txt
blackish-22.6.5.dist-info/RECORD
